pylint_mcp/cli.py
pylint_mcp-0.1.2.dist-info/COPYING
pylint_mcp-0.1.2.dist-info/METADATA
pylint_mcp-0.1.2.dist-info/WHEEL
pylint_mcp-0.1.2.dist-info/entry_points.txt
pylint_mcp-0.1.2.dist-info/RECORD
