Metadata-Version: 2.3
Name: pylint-mcp
Version: 0.1.2
Summary: MCP server providing pylint functionality
License: MIT
Author: Opti
Author-email: opti@will.respond.to.your.mom
Requires-Python: >=3.10
Classifier: License :: OSI Approved :: MIT License
Classifier: Programming Language :: Python :: 3
Classifier: Programming Language :: Python :: 3.10
Classifier: Programming Language :: Python :: 3.11
Classifier: Programming Language :: Python :: 3.12
Classifier: Programming Language :: Python :: 3.13
Requires-Dist: mcp[cli] (>=1.9.2,<2.0.0)
Requires-Dist: pylint (>=3.3.7,<4.0.0)
Project-URL: Homepage, https://codeberg.org/optimism/pylint-mcp
Project-URL: Issues, https://codeberg.org/optimism/pylint-mcp/issues
